.coveragerc
CHANGES.rst
LICENSE
MANIFEST.in
README.rst
setup.py
tox.ini
cosmic/__init__.py
cosmic/api.py
cosmic/client.py
cosmic/exceptions.py
cosmic/globals.py
cosmic/http.py
cosmic/legacy_teleport.py
cosmic/models.py
cosmic/testing.py
cosmic/tools.py
cosmic/types.py
cosmic.egg-info/PKG-INFO
cosmic.egg-info/SOURCES.txt
cosmic.egg-info/dependency_links.txt
cosmic.egg-info/requires.txt
cosmic.egg-info/top_level.txt
docs/Makefile
docs/source/changelog.rst
docs/source/conf.py
docs/source/guide.rst
docs/source/index.rst
docs/source/overview.rst
docs/source/reference.rst
docs/source/tutorial.rst
examples/__init__.py
examples/planetarium.py
examples/planetarium_test.py
examples/quotes.py
examples/words.py
examples/words_test.py
tests/__init__.py
tests/api_test.py
tests/docs_test.py
tests/http_test.py
tests/test_globals.py
tests/tools_test.py