Metadata-Version: 1.1
Name: cosmic
Version: 0.5.4
Summary: A tiny web API framework based on Teleport
Home-page: http://www.cosmic-api.com/docs/cosmic/python/
Author: 8313547 Canada Inc.
Author-email: alexei@boronine.com
License: MIT
Platform: UNKNOWN
Classifier: Development Status :: 4 - Beta
Classifier: License :: OSI Approved :: MIT License
Classifier: Intended Audience :: Developers
Classifier: Operating System :: OS Independent
Classifier: Programming Language :: Python
